orcommunicator/__init__.py
orcommunicator/orchannel.py
orcommunicator/orcommunicator.py
orcommunicator/orevent.py
orcommunicator/oritem.py
orcommunicator/ormessage.py
orcommunicator/orqueue.py
orcommunicator/ortopic.py
orcommunicator-0.0.11.dist-info/LICENSE.txt
orcommunicator-0.0.11.dist-info/METADATA
orcommunicator-0.0.11.dist-info/WHEEL
orcommunicator-0.0.11.dist-info/top_level.txt
orcommunicator-0.0.11.dist-info/RECORD
