Metadata-Version: 2.1
Name: orcommunicator
Version: 0.0.11
Summary: OpenResearch microservices communication management.
Home-page: https://github.com/leonardomra/orcommunicator
Author: Leonardo de Araújo
Author-email: dearaujo@uni-bremen.de
License: UNKNOWN
Platform: UNKNOWN
Classifier: Programming Language :: Python :: 3
Classifier: License :: OSI Approved :: MIT License
Classifier: Operating System :: OS Independent
Requires-Python: >=3.6
License-File: LICENSE.txt
Requires-Dist: boto3 (==1.14.25)
Requires-Dist: Flask (>=1.0.4)
Requires-Dist: ordbhandler (>=0.0.1)
